Containerfile
HISTORY.md
LICENSE
MANIFEST.in
README.md
requirements-test.txt
requirements.txt
setup.py
pysockmmsg/VERSION
pysockmmsg/__init__.py
pysockmmsg/base.py
pysockmmsg.egg-info/PKG-INFO
pysockmmsg.egg-info/SOURCES.txt
pysockmmsg.egg-info/dependency_links.txt
pysockmmsg.egg-info/requires.txt
pysockmmsg.egg-info/top_level.txt
pysockmmsg/__pycache__/__init__.cpython-39.pyc
pysockmmsg/__pycache__/base.cpython-39.pyc
tests/__init__.py
tests/conftest.py
tests/test_base.py
tests/test_performance.py
tests/__pycache__/__init__.cpython-39.pyc
tests/__pycache__/conftest.cpython-39-pytest-6.2.4.pyc
tests/__pycache__/conftest.cpython-39.pyc
tests/__pycache__/test_base.cpython-39-pytest-6.2.4.pyc
tests/__pycache__/test_base.cpython-39.pyc
tests/__pycache__/test_performance.cpython-39-pytest-6.2.4.pyc
tests/cffi/foo.py