Metadata-Version: 2.1
Name: pysockmmsg
Version: 0.0.2
Summary: Awesome pysockmmsg created by pappacena
Home-page: https://github.com/pappacena/pysockmmsg/
Author: pappacena
License: UNKNOWN
Platform: UNKNOWN
Provides-Extra: test
